<?xml version='1.0' encoding='cp1251'?>
<offers>
  <offer>
    <price>73.0</price>
    <code source="neiron">218</code>
  </offer>
  <offer>
    <price>82.0</price>
    <code source="neiron">161</code>
  </offer>
  <offer>
    <price>77.0</price>
    <code source="neiron">135</code>
  </offer>
  <offer>
    <price>24.5</price>
    <code source="neiron">149</code>
  </offer>
  <offer>
    <price>13.5</price>
    <code source="neiron">99</code>
  </offer>
  <offer>
    <price>27.0</price>
    <code source="neiron">194</code>
  </offer>
  <offer>
    <price>54.0</price>
    <code source="neiron">217</code>
  </offer>
  <offer>
    <price>18.5</price>
    <code source="neiron">229</code>
  </offer>
  <offer>
    <price>39.5</price>
    <code source="neiron">205</code>
  </offer>
  <offer>
    <price>54.0</price>
    <code source="neiron">78</code>
  </offer>
  <offer>
    <price>38.0</price>
    <code source="neiron">113</code>
  </offer>
  <offer>
    <price>42.0</price>
    <code source="neiron">206</code>
  </offer>
  <offer>
    <price>116.0</price>
    <code source="neiron">200</code>
  </offer>
  <offer>
    <price>37.0</price>
    <code source="neiron">127</code>
  </offer>
  <offer>
    <price>42.5</price>
    <code source="neiron">208</code>
  </offer>
  <offer>
    <price>20.5</price>
    <code source="neiron">123</code>
  </offer>
  <offer>
    <price>44.5</price>
    <code source="neiron">108</code>
  </offer>
  <offer>
    <price>108.0</price>
    <code source="neiron">195</code>
  </offer>
  <offer>
    <price>45.0</price>
    <code source="neiron">274</code>
  </offer>
  <offer>
    <price>40.0</price>
    <code source="neiron">207</code>
  </offer>
  <offer>
    <price>65.5</price>
    <code source="neiron">72</code>
  </offer>
  <offer>
    <price>33.5</price>
    <code source="neiron">134</code>
  </offer>
  <offer>
    <price>49.0</price>
    <code source="neiron">159</code>
  </offer>
  <offer>
    <price>44.5</price>
    <code source="neiron">203</code>
  </offer>
</offers>
